labmateai/__init__.py
labmateai/alembic.ini
labmateai/cli.py
labmateai/data_loader.py
labmateai/graph.py
labmateai/labmateai_db.py
labmateai/models.py
labmateai/tool.py
labmateai/tree.py
labmateai/alembic/env.py
labmateai/alembic/versions/697518134a33_removed_fake_data_used_for_upgrading_.py
labmateai/alembic/versions/e32bdffdf6d8_recreate_migration_tracking.py
labmateai/recommenders/__init__.py
labmateai/recommenders/collaborative_recommender.py
labmateai/recommenders/content_based_recommender.py
labmateai/recommenders/hybrid_recommender.py
labmateai/recommenders/recommender_interface.py
labmateai/tests/__init__.py
labmateai/tests/test_cli.py
labmateai/tests/test_collaborative_recommender.py
labmateai/tests/test_content_based_recommender.py
labmateai/tests/test_data_loader.py
labmateai/tests/test_graph.py
labmateai/tests/test_hybrid_recommender.py
labmateai/tests/test_labmateai_db.py
labmateai/tests/test_recommender_interface.py
labmateai/tests/test_tool.py
labmateai/tests/test_tree.py
labmateai-2.0.5.dist-info/LICENSE
labmateai-2.0.5.dist-info/METADATA
labmateai-2.0.5.dist-info/WHEEL
labmateai-2.0.5.dist-info/entry_points.txt
labmateai-2.0.5.dist-info/top_level.txt
labmateai-2.0.5.dist-info/RECORD
