Metadata-Version: 2.1
Name: labmateai
Version: 2.0.5
Summary: An AI-powered recommendation system for laboratory tools and software.
Home-page: https://github.com/RLTree/LabMateAI
Author: Terry Noblin
Author-email: Terry Noblin <tnoblin@health.ucsd.edu>
License: MIT
Project-URL: Bug Reports, https://github.com/RLTree/LabMateAI/issues
Project-URL: Source, https://github.com/RLTree/LabMateAI
Keywords: AI,Recommendation System,Laboratory Tools,Scientific Software,Bioinformatics
Classifier: Programming Language :: Python :: 3.12
Classifier: Operating System :: OS Independent
Classifier: Intended Audience :: Science/Research
Classifier: Topic :: Scientific/Engineering :: Artificial Intelligence
Classifier: License :: OSI Approved :: MIT License
Requires-Python: >=3.12
License-File: LICENSE
Requires-Dist: networkx==2.8.8
Requires-Dist: numpy>=1.23.5
Requires-Dist: prompt-toolkit>=3.0.0
Requires-Dist: pandas>=1.5.3
Requires-Dist: scikit-learn>=1.1.3
Requires-Dist: matplotlib>=3.6.2
Requires-Dist: flask>=2.2.2
Requires-Dist: requests>=2.28.1
Requires-Dist: scipy>=1.9.3
Requires-Dist: jinja2>=3.1.2
Requires-Dist: gunicorn>=20.1.0
Requires-Dist: psycopg2-binary>=2.9.0
Requires-Dist: python-dotenv>=0.19.1
Requires-Dist: sqlalchemy>=1.4.31
Requires-Dist: alembic>=1.7.4
Provides-Extra: dev
Requires-Dist: pytest>=7.4.0; extra == "dev"
Requires-Dist: pytest-cov>=4.0.0; extra == "dev"
Requires-Dist: pytest-xdist>=2.4.0; extra == "dev"
Requires-Dist: pytest-asyncio>=0.20.3; extra == "dev"
Requires-Dist: pytest-mock>=3.11.1; extra == "dev"
Requires-Dist: unittest-xml-reporting>=3.0.4; extra == "dev"
Requires-Dist: flake8>=6.1.0; extra == "dev"
Requires-Dist: mock>=4.0.3; extra == "dev"
Provides-Extra: docs
Requires-Dist: sphinx>=4.0.0; extra == "docs"
Requires-Dist: furo>=2021.8.14; extra == "docs"
